machine_learning_package/__init__.py
machine_learning_package-0.1.2.dist-info/METADATA
machine_learning_package-0.1.2.dist-info/WHEEL
machine_learning_package-0.1.2.dist-info/top_level.txt
machine_learning_package-0.1.2.dist-info/RECORD
