Metadata-Version: 2.1
Name: machine-learning-package
Version: 0.1.2
Summary: A package to import essential machine learning libraries
Home-page: https://github.com/JionKato/machine_learning_package
Author: Jion
Author-email: s2022042@stu.musasino-u.ac.jp
Classifier: Programming Language :: Python :: 3
Classifier: License :: OSI Approved :: MIT License
Classifier: Operating System :: OS Independent
Requires-Python: >=3.6
Requires-Dist: numpy
Requires-Dist: pandas
Requires-Dist: matplotlib
Requires-Dist: seaborn
Requires-Dist: scikit-learn
Requires-Dist: tensorflow
Requires-Dist: keras
